rpmvenv_macros/__init__.py
rpmvenv_macros/macros/__init__.py
rpmvenv_macros/macros/macros.py
rpmvenv_macros-0.0.1.dist-info/METADATA
rpmvenv_macros-0.0.1.dist-info/WHEEL
rpmvenv_macros-0.0.1.dist-info/entry_points.txt
rpmvenv_macros-0.0.1.dist-info/top_level.txt
rpmvenv_macros-0.0.1.dist-info/RECORD
